README.md
pyproject.toml
setup.cfg
src/rfc7748/__init__.py
src/rfc7748/rfc7748.py
src/rfc7748.egg-info/PKG-INFO
src/rfc7748.egg-info/SOURCES.txt
src/rfc7748.egg-info/dependency_links.txt
src/rfc7748.egg-info/top_level.txt