Metadata-Version: 2.1
Name: rfc7748
Version: 0.0.1
Summary: A pure Python implemention of rfc7748
Home-page: https://github.com/1ocalhost/rfc7748
Author: 1ocalhost
Classifier: Programming Language :: Python
Classifier: License :: Public Domain
Classifier: Operating System :: OS Independent
